Spruce_db-0.2.3-py2.7-nspkg.pth
Spruce_db-0.2.3.dist-info/top_level.txt
Spruce_db-0.2.3.dist-info/RECORD
Spruce_db-0.2.3.dist-info/pydist.json
Spruce_db-0.2.3.dist-info/WHEEL
Spruce_db-0.2.3.dist-info/namespace_packages.txt
Spruce_db-0.2.3.dist-info/METADATA
Spruce_db-0.2.3.dist-info/entry_points.txt
Spruce_db-0.2.3.dist-info/DESCRIPTION.rst
spruce/db/_exc.py
spruce/db/_types.py
spruce/db/_connparams.py
spruce/db/_engines.py
spruce/db/_time.py
spruce/db/__init__.py
spruce/db/orm/_hybrid.py
spruce/db/orm/__init__.py
