Metadata-Version: 2.0
Name: Spruce-db
Version: 0.2.3
Summary: Database interaction
Home-page: UNKNOWN
Author: Ivan D Vasin
Author-email: nisavid@gmail.com
License: GNU LESSER GENERAL PUBLIC LICENSE
Requires-Dist: sqlalchemy
Requires-Dist: spruce-collections
Requires-Dist: spruce-datetime
Requires-Dist: spruce-lang
Requires-Dist: spruce-settings
